allauth_saml2/__init__.py
allauth_saml2/client.py
allauth_saml2/provider.py
allauth_saml2/urls.py
allauth_saml2/views.py
django_allauth_saml2-0.2.0.dist-info/LICENSE
django_allauth_saml2-0.2.0.dist-info/METADATA
django_allauth_saml2-0.2.0.dist-info/WHEEL
django_allauth_saml2-0.2.0.dist-info/top_level.txt
django_allauth_saml2-0.2.0.dist-info/RECORD
