Metadata-Version: 2.1
Name: django-allauth-saml2
Version: 0.2.0
Summary: Django AllAuth Saml2 provider
Home-page: https://github.com/adevolutio/allauth_saml2
Author: David Vaz
Author-email: dvaz@evolutio.pt
License: MIT
Keywords: allauth_saml2
Platform: UNKNOWN
Classifier: Development Status :: 3 - Alpha
Classifier: Framework :: Django
Classifier: Intended Audience :: Developers
Classifier: Operating System :: OS Independent
Classifier: Natural Language :: English
Classifier: Programming Language :: Python :: 3
Requires-Dist: django (>=2.2)
Requires-Dist: django-allauth (>=0.43.0)
Requires-Dist: pysaml2 (==5.0.0)
